{
  "SPDXID": "SPDXRef-DOCUMENT",
  "creationInfo": {
    "comment": "This document was created by analyzing packages created during the build.",
    "created": "2022-11-24T14:11:34Z",
    "creators": [
      "Tool: OpenEmbedded Core create-spdx.bbclass",
      "Organization: OpenEmbedded ()",
      "Person: N/A ()"
    ],
    "licenseListVersion": "3.14"
  },
  "dataLicense": "CC0-1.0",
  "documentNamespace": "http://spdx.org/spdxdoc/glibc-localedata-hu-hu-a9b5266a-f9f6-5620-ae2a-7be74f48b190",
  "externalDocumentRefs": [
    {
      "checksum": {
        "algorithm": "SHA1",
        "checksumValue": "2c549e1c04cace954ec5c20c5020c444b132bd2b"
      },
      "externalDocumentId": "DocumentRef-recipe-glibc-locale",
      "spdxDocument": "http://spdx.org/spdxdoc/recipe-glibc-locale-47f2a024-76b3-5cce-b0ab-d34e50dc4570"
    }
  ],
  "files": [
    {
      "SPDXID": "SPDXRef-PackagedFile-glibc-localedata-hu-hu-1",
      "checksums": [
        {
          "algorithm": "SHA1",
          "checksumValue": "a1d10c4a9970ffbc158e5008ff9c0975c2cf244c"
        },
        {
          "algorithm": "SHA256",
          "checksumValue": "2de829d7a102f59a4b30ca95b11cc30ea4140cabe6a1301a966306ed814fd807"
        }
      ],
      "copyrightText": "NOASSERTION",
      "fileName": "usr/share/i18n/locales/hu_HU",
      "fileTypes": [
        "BINARY"
      ],
      "licenseConcluded": "NOASSERTION",
      "licenseInfoInFiles": [
        "NOASSERTION"
      ]
    }
  ],
  "name": "glibc-localedata-hu-hu",
  "packages": [
    {
      "SPDXID": "SPDXRef-Package-glibc-localedata-hu-hu",
      "copyrightText": "NOASSERTION",
      "downloadLocation": "NOASSERTION",
      "hasFiles": [
        "SPDXRef-PackagedFile-glibc-localedata-hu-hu-1"
      ],
      "licenseConcluded": "NOASSERTION",
      "licenseDeclared": "GPL-2.0-only AND LGPL-2.1-only",
      "licenseInfoFromFiles": [
        "NOASSERTION"
      ],
      "name": "glibc-localedata-hu-hu",
      "packageVerificationCode": {
        "packageVerificationCodeValue": "6133cad275d1429fcb666b6ac2c51a2dbd0614be"
      },
      "supplier": "Organization: OpenEmbedded ()",
      "versionInfo": "2.36"
    }
  ],
  "relationships": [
    {
      "relatedSpdxElement": "DocumentRef-recipe-glibc-locale:SPDXRef-Recipe-glibc-locale",
      "relationshipType": "GENERATED_FROM",
      "spdxElementId": "SPDXRef-Package-glibc-localedata-hu-hu"
    },
    {
      "relatedSpdxElement": "SPDXRef-Package-glibc-localedata-hu-hu",
      "relationshipType": "DESCRIBES",
      "spdxElementId": "SPDXRef-DOCUMENT"
    },
    {
      "relatedSpdxElement": "SPDXRef-PackagedFile-glibc-localedata-hu-hu-1",
      "relationshipType": "CONTAINS",
      "spdxElementId": "SPDXRef-Package-glibc-localedata-hu-hu"
    }
  ],
  "spdxVersion": "SPDX-2.2"
}
