{
  "SPDXID": "SPDXRef-DOCUMENT",
  "creationInfo": {
    "comment": "This document was created by analyzing packages created during the build.",
    "created": "2022-09-15T13:19:56Z",
    "creators": [
      "Tool: OpenEmbedded Core create-spdx.bbclass",
      "Organization: OpenEmbedded ()",
      "Person: N/A ()"
    ],
    "licenseListVersion": "3.14"
  },
  "dataLicense": "CC0-1.0",
  "documentNamespace": "http://spdx.org/spdxdoc/glibc-localedata-quz-pe-075e8bb0-022e-5ccc-8beb-9ea6adb9d768",
  "externalDocumentRefs": [
    {
      "checksum": {
        "algorithm": "SHA1",
        "checksumValue": "3504dc3db5634f1dcebcb54b04b2b2cfe047f1ed"
      },
      "externalDocumentId": "DocumentRef-recipe-glibc-locale",
      "spdxDocument": "http://spdx.org/spdxdoc/recipe-glibc-locale-47f2a024-76b3-5cce-b0ab-d34e50dc4570"
    }
  ],
  "files": [
    {
      "SPDXID": "SPDXRef-PackagedFile-glibc-localedata-quz-pe-1",
      "checksums": [
        {
          "algorithm": "SHA1",
          "checksumValue": "992ec5c69bb7eb5b5023db6ffed24363605838ff"
        },
        {
          "algorithm": "SHA256",
          "checksumValue": "32fd131926b7a56c052cd111fc2c85e1f32f003564364518c945e1cd80427594"
        }
      ],
      "copyrightText": "NOASSERTION",
      "fileName": "usr/share/i18n/locales/quz_PE",
      "fileTypes": [
        "BINARY"
      ],
      "licenseConcluded": "NOASSERTION",
      "licenseInfoInFiles": [
        "NOASSERTION"
      ]
    }
  ],
  "name": "glibc-localedata-quz-pe",
  "packages": [
    {
      "SPDXID": "SPDXRef-Package-glibc-localedata-quz-pe",
      "copyrightText": "NOASSERTION",
      "downloadLocation": "NOASSERTION",
      "hasFiles": [
        "SPDXRef-PackagedFile-glibc-localedata-quz-pe-1"
      ],
      "licenseConcluded": "NOASSERTION",
      "licenseDeclared": "GPL-2.0-only AND LGPL-2.1-only",
      "licenseInfoFromFiles": [
        "NOASSERTION"
      ],
      "name": "glibc-localedata-quz-pe",
      "packageVerificationCode": {
        "packageVerificationCodeValue": "d3a4ea5e8b789cef8012bd1ca6c983457313d634"
      },
      "supplier": "Organization: OpenEmbedded ()",
      "versionInfo": "2.36"
    }
  ],
  "relationships": [
    {
      "relatedSpdxElement": "DocumentRef-recipe-glibc-locale:SPDXRef-Recipe-glibc-locale",
      "relationshipType": "GENERATED_FROM",
      "spdxElementId": "SPDXRef-Package-glibc-localedata-quz-pe"
    },
    {
      "relatedSpdxElement": "SPDXRef-Package-glibc-localedata-quz-pe",
      "relationshipType": "DESCRIBES",
      "spdxElementId": "SPDXRef-DOCUMENT"
    },
    {
      "relatedSpdxElement": "SPDXRef-PackagedFile-glibc-localedata-quz-pe-1",
      "relationshipType": "CONTAINS",
      "spdxElementId": "SPDXRef-Package-glibc-localedata-quz-pe"
    }
  ],
  "spdxVersion": "SPDX-2.2"
}
