{
  "SPDXID": "SPDXRef-DOCUMENT",
  "creationInfo": {
    "comment": "This document was created by analyzing packages created during the build.",
    "created": "2022-09-08T13:31:52Z",
    "creators": [
      "Tool: OpenEmbedded Core create-spdx.bbclass",
      "Organization: OpenEmbedded ()",
      "Person: N/A ()"
    ],
    "licenseListVersion": "3.14"
  },
  "dataLicense": "CC0-1.0",
  "documentNamespace": "http://spdx.org/spdxdoc/glibc-binary-localedata-lt-lt.iso-8859-13-50bd949e-e098-542b-b942-757b9cde90f5",
  "externalDocumentRefs": [
    {
      "checksum": {
        "algorithm": "SHA1",
        "checksumValue": "5afe33d901fb00f80377610390848e284d5bf8be"
      },
      "externalDocumentId": "DocumentRef-recipe-glibc-locale",
      "spdxDocument": "http://spdx.org/spdxdoc/recipe-glibc-locale-47f2a024-76b3-5cce-b0ab-d34e50dc4570"
    }
  ],
  "files": [
    {
      "SPDXID": "SPDXRef-PackagedFile-glibc-binary-localedata-lt-lt.iso-8859-13-1",
      "checksums": [
        {
          "algorithm": "SHA1",
          "checksumValue": "a618822d3e29c9da2ca049c0491a727c871d922d"
        },
        {
          "algorithm": "SHA256",
          "checksumValue": "7411c0d746c78939ed7992cea3543b7d743f873a7a8f294d860b084cf23ab3d2"
        }
      ],
      "copyrightText": "NOASSERTION",
      "fileName": "usr/lib/locale/lt_LT.ISO-8859-13/LC_MEASUREMENT",
      "fileTypes": [
        "BINARY"
      ],
      "licenseConcluded": "NOASSERTION",
      "licenseInfoInFiles": [
        "NOASSERTION"
      ]
    },
    {
      "SPDXID": "SPDXRef-PackagedFile-glibc-binary-localedata-lt-lt.iso-8859-13-2",
      "checksums": [
        {
          "algorithm": "SHA1",
          "checksumValue": "b72b438cf429e2df14c4ef0e62c433b61350c0c1"
        },
        {
          "algorithm": "SHA256",
          "checksumValue": "6f1f256ca889ddc6cbf79c51abd2f2142d7d940a93a5dce9e71bafb96aa992d3"
        }
      ],
      "copyrightText": "NOASSERTION",
      "fileName": "usr/lib/locale/lt_LT.ISO-8859-13/LC_NUMERIC",
      "fileTypes": [
        "BINARY"
      ],
      "licenseConcluded": "NOASSERTION",
      "licenseInfoInFiles": [
        "NOASSERTION"
      ]
    },
    {
      "SPDXID": "SPDXRef-PackagedFile-glibc-binary-localedata-lt-lt.iso-8859-13-3",
      "checksums": [
        {
          "algorithm": "SHA1",
          "checksumValue": "fe198ea0386fca1c54f0fffee38ada875bca36a8"
        },
        {
          "algorithm": "SHA256",
          "checksumValue": "112341b7d9de7ddb256ac15f51920b81f5419d07d40c55250de15f7a2b01ef82"
        }
      ],
      "copyrightText": "NOASSERTION",
      "fileName": "usr/lib/locale/lt_LT.ISO-8859-13/LC_ADDRESS",
      "fileTypes": [
        "BINARY"
      ],
      "licenseConcluded": "NOASSERTION",
      "licenseInfoInFiles": [
        "NOASSERTION"
      ]
    },
    {
      "SPDXID": "SPDXRef-PackagedFile-glibc-binary-localedata-lt-lt.iso-8859-13-4",
      "checksums": [
        {
          "algorithm": "SHA1",
          "checksumValue": "82ff01bf91596b9b87b3d554a08e67b1ac6fd985"
        },
        {
          "algorithm": "SHA256",
          "checksumValue": "fa21f59b2ff5b0326c208b40be5677d0e891fb47909d01fa5c90f0cf57dbb5f3"
        }
      ],
      "copyrightText": "NOASSERTION",
      "fileName": "usr/lib/locale/lt_LT.ISO-8859-13/LC_CTYPE",
      "fileTypes": [
        "BINARY"
      ],
      "licenseConcluded": "NOASSERTION",
      "licenseInfoInFiles": [
        "NOASSERTION"
      ]
    },
    {
      "SPDXID": "SPDXRef-PackagedFile-glibc-binary-localedata-lt-lt.iso-8859-13-5",
      "checksums": [
        {
          "algorithm": "SHA1",
          "checksumValue": "7390a55db357a1905ae2d3c3658f49d8d381ca51"
        },
        {
          "algorithm": "SHA256",
          "checksumValue": "d7a236e32b6f42bbd9d41d87261d77972fcf8e86cea33e805d771542faee6894"
        }
      ],
      "copyrightText": "NOASSERTION",
      "fileName": "usr/lib/locale/lt_LT.ISO-8859-13/LC_IDENTIFICATION",
      "fileTypes": [
        "BINARY"
      ],
      "licenseConcluded": "NOASSERTION",
      "licenseInfoInFiles": [
        "NOASSERTION"
      ]
    },
    {
      "SPDXID": "SPDXRef-PackagedFile-glibc-binary-localedata-lt-lt.iso-8859-13-6",
      "checksums": [
        {
          "algorithm": "SHA1",
          "checksumValue": "47e0e83e2182667f66e485ef84b7624cf8cab858"
        },
        {
          "algorithm": "SHA256",
          "checksumValue": "45f9775293852c74b791edd81371de178ec6fe8044ca39e5ede310e7a8f20846"
        }
      ],
      "copyrightText": "NOASSERTION",
      "fileName": "usr/lib/locale/lt_LT.ISO-8859-13/LC_NAME",
      "fileTypes": [
        "BINARY"
      ],
      "licenseConcluded": "NOASSERTION",
      "licenseInfoInFiles": [
        "NOASSERTION"
      ]
    },
    {
      "SPDXID": "SPDXRef-PackagedFile-glibc-binary-localedata-lt-lt.iso-8859-13-7",
      "checksums": [
        {
          "algorithm": "SHA1",
          "checksumValue": "052aa00daedcc697ff8418362efefbe27cf59851"
        },
        {
          "algorithm": "SHA256",
          "checksumValue": "507182c589cd5d30bed2943be68aac8d0dc6316d3a5621ac7a632ebf0151069a"
        }
      ],
      "copyrightText": "NOASSERTION",
      "fileName": "usr/lib/locale/lt_LT.ISO-8859-13/LC_COLLATE",
      "fileTypes": [
        "BINARY"
      ],
      "licenseConcluded": "NOASSERTION",
      "licenseInfoInFiles": [
        "NOASSERTION"
      ]
    },
    {
      "SPDXID": "SPDXRef-PackagedFile-glibc-binary-localedata-lt-lt.iso-8859-13-8",
      "checksums": [
        {
          "algorithm": "SHA1",
          "checksumValue": "3c3b8b2c3d65e54920dffa0b7ed07e1bf4b4261c"
        },
        {
          "algorithm": "SHA256",
          "checksumValue": "bab8309bfa1f83dec863392e946eede4d7804e2173e74661d4a8b8d439ce7b6f"
        }
      ],
      "copyrightText": "NOASSERTION",
      "fileName": "usr/lib/locale/lt_LT.ISO-8859-13/LC_TELEPHONE",
      "fileTypes": [
        "BINARY"
      ],
      "licenseConcluded": "NOASSERTION",
      "licenseInfoInFiles": [
        "NOASSERTION"
      ]
    },
    {
      "SPDXID": "SPDXRef-PackagedFile-glibc-binary-localedata-lt-lt.iso-8859-13-9",
      "checksums": [
        {
          "algorithm": "SHA1",
          "checksumValue": "5fbe58886170e8af1af2e0dfc221ce16457ebfea"
        },
        {
          "algorithm": "SHA256",
          "checksumValue": "f270c1a5ea72e00164a3c4dd9148f1c9cd2b47d974eda092de150b4c408e0b83"
        }
      ],
      "copyrightText": "NOASSERTION",
      "fileName": "usr/lib/locale/lt_LT.ISO-8859-13/LC_TIME",
      "fileTypes": [
        "BINARY"
      ],
      "licenseConcluded": "NOASSERTION",
      "licenseInfoInFiles": [
        "NOASSERTION"
      ]
    },
    {
      "SPDXID": "SPDXRef-PackagedFile-glibc-binary-localedata-lt-lt.iso-8859-13-10",
      "checksums": [
        {
          "algorithm": "SHA1",
          "checksumValue": "64ed7988c311a5f5e2cb35066fd9d7de1dbeb832"
        },
        {
          "algorithm": "SHA256",
          "checksumValue": "9ab19f3ac11d8dbafa99b9e33509087e3b253d952406af059058244406f4650b"
        }
      ],
      "copyrightText": "NOASSERTION",
      "fileName": "usr/lib/locale/lt_LT.ISO-8859-13/LC_PAPER",
      "fileTypes": [
        "BINARY"
      ],
      "licenseConcluded": "NOASSERTION",
      "licenseInfoInFiles": [
        "NOASSERTION"
      ]
    },
    {
      "SPDXID": "SPDXRef-PackagedFile-glibc-binary-localedata-lt-lt.iso-8859-13-11",
      "checksums": [
        {
          "algorithm": "SHA1",
          "checksumValue": "e9506a0d5be1b8a795cb9325013ae2a940dc23a2"
        },
        {
          "algorithm": "SHA256",
          "checksumValue": "a05e7c888e1a94d68e6e85284a76f5eb5ca849e88140d797779aa74a9ee734d0"
        }
      ],
      "copyrightText": "NOASSERTION",
      "fileName": "usr/lib/locale/lt_LT.ISO-8859-13/LC_MONETARY",
      "fileTypes": [
        "BINARY"
      ],
      "licenseConcluded": "NOASSERTION",
      "licenseInfoInFiles": [
        "NOASSERTION"
      ]
    },
    {
      "SPDXID": "SPDXRef-PackagedFile-glibc-binary-localedata-lt-lt.iso-8859-13-12",
      "checksums": [
        {
          "algorithm": "SHA1",
          "checksumValue": "28413982cd6d8e973aaff3ec2e85adb2e8089c31"
        },
        {
          "algorithm": "SHA256",
          "checksumValue": "9b23c65dd87cf96e7a5e10a011a28f789908429057babfb9ebfecefd16430cc3"
        }
      ],
      "copyrightText": "NOASSERTION",
      "fileName": "usr/lib/locale/lt_LT.ISO-8859-13/LC_MESSAGES/SYS_LC_MESSAGES",
      "fileTypes": [
        "BINARY"
      ],
      "licenseConcluded": "NOASSERTION",
      "licenseInfoInFiles": [
        "NOASSERTION"
      ]
    }
  ],
  "name": "glibc-binary-localedata-lt-lt.iso-8859-13",
  "packages": [
    {
      "SPDXID": "SPDXRef-Package-glibc-binary-localedata-lt-lt.iso-8859-13",
      "copyrightText": "NOASSERTION",
      "downloadLocation": "NOASSERTION",
      "hasFiles": [
        "SPDXRef-PackagedFile-glibc-binary-localedata-lt-lt.iso-8859-13-1",
        "SPDXRef-PackagedFile-glibc-binary-localedata-lt-lt.iso-8859-13-2",
        "SPDXRef-PackagedFile-glibc-binary-localedata-lt-lt.iso-8859-13-3",
        "SPDXRef-PackagedFile-glibc-binary-localedata-lt-lt.iso-8859-13-4",
        "SPDXRef-PackagedFile-glibc-binary-localedata-lt-lt.iso-8859-13-5",
        "SPDXRef-PackagedFile-glibc-binary-localedata-lt-lt.iso-8859-13-6",
        "SPDXRef-PackagedFile-glibc-binary-localedata-lt-lt.iso-8859-13-7",
        "SPDXRef-PackagedFile-glibc-binary-localedata-lt-lt.iso-8859-13-8",
        "SPDXRef-PackagedFile-glibc-binary-localedata-lt-lt.iso-8859-13-9",
        "SPDXRef-PackagedFile-glibc-binary-localedata-lt-lt.iso-8859-13-10",
        "SPDXRef-PackagedFile-glibc-binary-localedata-lt-lt.iso-8859-13-11",
        "SPDXRef-PackagedFile-glibc-binary-localedata-lt-lt.iso-8859-13-12"
      ],
      "licenseConcluded": "NOASSERTION",
      "licenseDeclared": "GPL-2.0-only AND LGPL-2.1-only",
      "licenseInfoFromFiles": [
        "NOASSERTION"
      ],
      "name": "glibc-binary-localedata-lt-lt.iso-8859-13",
      "packageVerificationCode": {
        "packageVerificationCodeValue": "b180819065a4e8af93c5899370c8eadedc10aefb"
      },
      "supplier": "Organization: OpenEmbedded ()",
      "versionInfo": "2.36"
    }
  ],
  "relationships": [
    {
      "relatedSpdxElement": "DocumentRef-recipe-glibc-locale:SPDXRef-Recipe-glibc-locale",
      "relationshipType": "GENERATED_FROM",
      "spdxElementId": "SPDXRef-Package-glibc-binary-localedata-lt-lt.iso-8859-13"
    },
    {
      "relatedSpdxElement": "SPDXRef-Package-glibc-binary-localedata-lt-lt.iso-8859-13",
      "relationshipType": "DESCRIBES",
      "spdxElementId": "SPDXRef-DOCUMENT"
    },
    {
      "relatedSpdxElement": "SPDXRef-PackagedFile-glibc-binary-localedata-lt-lt.iso-8859-13-1",
      "relationshipType": "CONTAINS",
      "spdxElementId": "SPDXRef-Package-glibc-binary-localedata-lt-lt.iso-8859-13"
    },
    {
      "relatedSpdxElement": "SPDXRef-PackagedFile-glibc-binary-localedata-lt-lt.iso-8859-13-2",
      "relationshipType": "CONTAINS",
      "spdxElementId": "SPDXRef-Package-glibc-binary-localedata-lt-lt.iso-8859-13"
    },
    {
      "relatedSpdxElement": "SPDXRef-PackagedFile-glibc-binary-localedata-lt-lt.iso-8859-13-3",
      "relationshipType": "CONTAINS",
      "spdxElementId": "SPDXRef-Package-glibc-binary-localedata-lt-lt.iso-8859-13"
    },
    {
      "relatedSpdxElement": "SPDXRef-PackagedFile-glibc-binary-localedata-lt-lt.iso-8859-13-4",
      "relationshipType": "CONTAINS",
      "spdxElementId": "SPDXRef-Package-glibc-binary-localedata-lt-lt.iso-8859-13"
    },
    {
      "relatedSpdxElement": "SPDXRef-PackagedFile-glibc-binary-localedata-lt-lt.iso-8859-13-5",
      "relationshipType": "CONTAINS",
      "spdxElementId": "SPDXRef-Package-glibc-binary-localedata-lt-lt.iso-8859-13"
    },
    {
      "relatedSpdxElement": "SPDXRef-PackagedFile-glibc-binary-localedata-lt-lt.iso-8859-13-6",
      "relationshipType": "CONTAINS",
      "spdxElementId": "SPDXRef-Package-glibc-binary-localedata-lt-lt.iso-8859-13"
    },
    {
      "relatedSpdxElement": "SPDXRef-PackagedFile-glibc-binary-localedata-lt-lt.iso-8859-13-7",
      "relationshipType": "CONTAINS",
      "spdxElementId": "SPDXRef-Package-glibc-binary-localedata-lt-lt.iso-8859-13"
    },
    {
      "relatedSpdxElement": "SPDXRef-PackagedFile-glibc-binary-localedata-lt-lt.iso-8859-13-8",
      "relationshipType": "CONTAINS",
      "spdxElementId": "SPDXRef-Package-glibc-binary-localedata-lt-lt.iso-8859-13"
    },
    {
      "relatedSpdxElement": "SPDXRef-PackagedFile-glibc-binary-localedata-lt-lt.iso-8859-13-9",
      "relationshipType": "CONTAINS",
      "spdxElementId": "SPDXRef-Package-glibc-binary-localedata-lt-lt.iso-8859-13"
    },
    {
      "relatedSpdxElement": "SPDXRef-PackagedFile-glibc-binary-localedata-lt-lt.iso-8859-13-10",
      "relationshipType": "CONTAINS",
      "spdxElementId": "SPDXRef-Package-glibc-binary-localedata-lt-lt.iso-8859-13"
    },
    {
      "relatedSpdxElement": "SPDXRef-PackagedFile-glibc-binary-localedata-lt-lt.iso-8859-13-11",
      "relationshipType": "CONTAINS",
      "spdxElementId": "SPDXRef-Package-glibc-binary-localedata-lt-lt.iso-8859-13"
    },
    {
      "relatedSpdxElement": "SPDXRef-PackagedFile-glibc-binary-localedata-lt-lt.iso-8859-13-12",
      "relationshipType": "CONTAINS",
      "spdxElementId": "SPDXRef-Package-glibc-binary-localedata-lt-lt.iso-8859-13"
    }
  ],
  "spdxVersion": "SPDX-2.2"
}
