{
  "SPDXID": "SPDXRef-DOCUMENT",
  "creationInfo": {
    "comment": "This document was created by analyzing packages created during the build.",
    "created": "2023-01-26T13:57:35Z",
    "creators": [
      "Tool: OpenEmbedded Core create-spdx.bbclass",
      "Organization: OpenEmbedded ()",
      "Person: N/A ()"
    ],
    "licenseListVersion": "3.14"
  },
  "dataLicense": "CC0-1.0",
  "documentNamespace": "http://spdx.org/spdxdoc/grep-locale-de-b1ed090e-169d-5902-bca4-abf4326c2fd1",
  "externalDocumentRefs": [
    {
      "checksum": {
        "algorithm": "SHA1",
        "checksumValue": "768cb87e97fc7191d52c95f536de44a99f9d6368"
      },
      "externalDocumentId": "DocumentRef-recipe-grep",
      "spdxDocument": "http://spdx.org/spdxdoc/recipe-grep-b91d24e2-5f12-573a-927d-97e5d2895564"
    }
  ],
  "files": [
    {
      "SPDXID": "SPDXRef-PackagedFile-grep-locale-de-1",
      "checksums": [
        {
          "algorithm": "SHA1",
          "checksumValue": "4569aca88bfdc3f8efdad003e230a9779fc1b1e8"
        },
        {
          "algorithm": "SHA256",
          "checksumValue": "f26269de946db502e6b3dff6bc9fea9e7dccce65ef7678ff0c87f90adddd55f7"
        }
      ],
      "copyrightText": "NOASSERTION",
      "fileName": "usr/share/locale/de/LC_MESSAGES/grep.mo",
      "fileTypes": [
        "BINARY"
      ],
      "licenseConcluded": "NOASSERTION",
      "licenseInfoInFiles": [
        "NOASSERTION"
      ]
    }
  ],
  "name": "grep-locale-de",
  "packages": [
    {
      "SPDXID": "SPDXRef-Package-grep-locale-de",
      "copyrightText": "NOASSERTION",
      "downloadLocation": "NOASSERTION",
      "hasFiles": [
        "SPDXRef-PackagedFile-grep-locale-de-1"
      ],
      "licenseConcluded": "NOASSERTION",
      "licenseDeclared": "GPL-3.0-only",
      "licenseInfoFromFiles": [
        "NOASSERTION"
      ],
      "name": "grep-locale-de",
      "packageVerificationCode": {
        "packageVerificationCodeValue": "2fa22312086547fe7b88b527ac8f4ce750106722"
      },
      "supplier": "Organization: OpenEmbedded ()",
      "versionInfo": "3.8"
    }
  ],
  "relationships": [
    {
      "relatedSpdxElement": "DocumentRef-recipe-grep:SPDXRef-Recipe-grep",
      "relationshipType": "GENERATED_FROM",
      "spdxElementId": "SPDXRef-Package-grep-locale-de"
    },
    {
      "relatedSpdxElement": "SPDXRef-Package-grep-locale-de",
      "relationshipType": "DESCRIBES",
      "spdxElementId": "SPDXRef-DOCUMENT"
    },
    {
      "relatedSpdxElement": "SPDXRef-PackagedFile-grep-locale-de-1",
      "relationshipType": "CONTAINS",
      "spdxElementId": "SPDXRef-Package-grep-locale-de"
    }
  ],
  "spdxVersion": "SPDX-2.2"
}
