{
  "SPDXID": "SPDXRef-DOCUMENT",
  "creationInfo": {
    "comment": "This document was created by analyzing packages created during the build.",
    "created": "2022-11-03T11:30:19Z",
    "creators": [
      "Tool: OpenEmbedded Core create-spdx.bbclass",
      "Organization: OpenEmbedded ()",
      "Person: N/A ()"
    ],
    "licenseListVersion": "3.14"
  },
  "dataLicense": "CC0-1.0",
  "documentNamespace": "http://spdx.org/spdxdoc/libidn2-locale-fi-b92b083c-68bc-5cc1-b25b-01bb9e8db62f",
  "externalDocumentRefs": [
    {
      "checksum": {
        "algorithm": "SHA1",
        "checksumValue": "452e5efbf77a65d8ab40af35e2232aa73f3b82e0"
      },
      "externalDocumentId": "DocumentRef-recipe-libidn2",
      "spdxDocument": "http://spdx.org/spdxdoc/recipe-libidn2-84a7cdd0-ac50-5fc3-b90e-d89205bcf1b8"
    }
  ],
  "files": [
    {
      "SPDXID": "SPDXRef-PackagedFile-libidn2-locale-fi-1",
      "checksums": [
        {
          "algorithm": "SHA1",
          "checksumValue": "6705f0537c44d0b9dd2da88618b08c6b001a85ed"
        },
        {
          "algorithm": "SHA256",
          "checksumValue": "1592cebe94201b161ad361e8a1d18b5b79ffda5cb9d7d2cfce87729c47f70c5f"
        }
      ],
      "copyrightText": "NOASSERTION",
      "fileName": "usr/share/locale/fi/LC_MESSAGES/libidn2.mo",
      "fileTypes": [
        "BINARY"
      ],
      "licenseConcluded": "NOASSERTION",
      "licenseInfoInFiles": [
        "NOASSERTION"
      ]
    }
  ],
  "name": "libidn2-locale-fi",
  "packages": [
    {
      "SPDXID": "SPDXRef-Package-libidn2-locale-fi",
      "copyrightText": "NOASSERTION",
      "downloadLocation": "NOASSERTION",
      "hasFiles": [
        "SPDXRef-PackagedFile-libidn2-locale-fi-1"
      ],
      "licenseConcluded": "NOASSERTION",
      "licenseDeclared": "( GPL-2.0-or-later OR LGPL-3.0-only ) AND GPL-3.0-or-later AND Unicode-DFS-2016",
      "licenseInfoFromFiles": [
        "NOASSERTION"
      ],
      "name": "libidn2-locale-fi",
      "packageVerificationCode": {
        "packageVerificationCodeValue": "78314e877a773376490e9628df6d198c1fedeab5"
      },
      "supplier": "Organization: OpenEmbedded ()",
      "versionInfo": "2.3.3"
    }
  ],
  "relationships": [
    {
      "relatedSpdxElement": "DocumentRef-recipe-libidn2:SPDXRef-Recipe-libidn2",
      "relationshipType": "GENERATED_FROM",
      "spdxElementId": "SPDXRef-Package-libidn2-locale-fi"
    },
    {
      "relatedSpdxElement": "SPDXRef-Package-libidn2-locale-fi",
      "relationshipType": "DESCRIBES",
      "spdxElementId": "SPDXRef-DOCUMENT"
    },
    {
      "relatedSpdxElement": "SPDXRef-PackagedFile-libidn2-locale-fi-1",
      "relationshipType": "CONTAINS",
      "spdxElementId": "SPDXRef-Package-libidn2-locale-fi"
    }
  ],
  "spdxVersion": "SPDX-2.2"
}
