{
  "SPDXID": "SPDXRef-DOCUMENT",
  "creationInfo": {
    "comment": "This document was created by analyzing packages created during the build.",
    "created": "2022-08-25T12:16:02Z",
    "creators": [
      "Tool: OpenEmbedded Core create-spdx.bbclass",
      "Organization: OpenEmbedded ()",
      "Person: N/A ()"
    ],
    "licenseListVersion": "3.14"
  },
  "dataLicense": "CC0-1.0",
  "documentNamespace": "http://spdx.org/spdxdoc/perl-module-dbm-filter-null-deb97315-6608-530f-88a8-d235604cfa35",
  "externalDocumentRefs": [
    {
      "checksum": {
        "algorithm": "SHA1",
        "checksumValue": "465dea6f1e362a22314145ca8b05b2df6506b952"
      },
      "externalDocumentId": "DocumentRef-recipe-perl",
      "spdxDocument": "http://spdx.org/spdxdoc/recipe-perl-6f42614c-138d-5270-8ad2-6a8ebaf640d1"
    }
  ],
  "files": [
    {
      "SPDXID": "SPDXRef-PackagedFile-perl-module-dbm-filter-null-1",
      "checksums": [
        {
          "algorithm": "SHA1",
          "checksumValue": "a1cee6254b23328dde494d791df7685770dadf6d"
        },
        {
          "algorithm": "SHA256",
          "checksumValue": "4ca02d8100008d3fdfc2c8de9635cd3f586b463cc3c17f727b01a7f6b247f4da"
        }
      ],
      "copyrightText": "NOASSERTION",
      "fileName": "usr/lib/perl5/5.36.0/DBM_Filter/null.pm",
      "fileTypes": [
        "BINARY"
      ],
      "licenseConcluded": "NOASSERTION",
      "licenseInfoInFiles": [
        "NOASSERTION"
      ]
    }
  ],
  "name": "perl-module-dbm-filter-null",
  "packages": [
    {
      "SPDXID": "SPDXRef-Package-perl-module-dbm-filter-null",
      "copyrightText": "NOASSERTION",
      "downloadLocation": "NOASSERTION",
      "hasFiles": [
        "SPDXRef-PackagedFile-perl-module-dbm-filter-null-1"
      ],
      "licenseConcluded": "NOASSERTION",
      "licenseDeclared": "Artistic-1.0 OR GPL-1.0-or-later",
      "licenseInfoFromFiles": [
        "NOASSERTION"
      ],
      "name": "perl-module-dbm-filter-null",
      "packageVerificationCode": {
        "packageVerificationCodeValue": "0315304cf70294098ab33916d90bbd2a1a82ddc5"
      },
      "supplier": "Organization: OpenEmbedded ()",
      "versionInfo": "5.36.0"
    }
  ],
  "relationships": [
    {
      "relatedSpdxElement": "DocumentRef-recipe-perl:SPDXRef-Recipe-perl",
      "relationshipType": "GENERATED_FROM",
      "spdxElementId": "SPDXRef-Package-perl-module-dbm-filter-null"
    },
    {
      "relatedSpdxElement": "SPDXRef-Package-perl-module-dbm-filter-null",
      "relationshipType": "DESCRIBES",
      "spdxElementId": "SPDXRef-DOCUMENT"
    },
    {
      "relatedSpdxElement": "SPDXRef-PackagedFile-perl-module-dbm-filter-null-1",
      "relationshipType": "CONTAINS",
      "spdxElementId": "SPDXRef-Package-perl-module-dbm-filter-null"
    }
  ],
  "spdxVersion": "SPDX-2.2"
}
