{
  "SPDXID": "SPDXRef-DOCUMENT",
  "creationInfo": {
    "comment": "This document was created by analyzing packages created during the build.",
    "created": "2022-05-05T13:21:32Z",
    "creators": [
      "Tool: OpenEmbedded Core create-spdx.bbclass",
      "Organization: OpenEmbedded ()",
      "Person: N/A ()"
    ],
    "licenseListVersion": "3.14"
  },
  "dataLicense": "CC0-1.0",
  "documentNamespace": "http://spdx.org/spdxdoc/shadow-dbg-ae45f420-9b9c-51e7-bb8c-e8ac86865856",
  "externalDocumentRefs": [
    {
      "checksum": {
        "algorithm": "SHA1",
        "checksumValue": "a5c675038535272acd9bcfce1edb1492855c6d52"
      },
      "externalDocumentId": "DocumentRef-recipe-shadow",
      "spdxDocument": "http://spdx.org/spdxdoc/recipe-shadow-6845d95c-0853-56dd-b976-caae5a99461e"
    }
  ],
  "files": [
    {
      "SPDXID": "SPDXRef-PackagedFile-shadow-dbg-1",
      "checksums": [
        {
          "algorithm": "SHA1",
          "checksumValue": "6a4b27b1ed8c13f6dce5187c8079fe6300809e21"
        },
        {
          "algorithm": "SHA256",
          "checksumValue": "80f616974f4450f6596142b97508666fd8acbdff83b3d9d0fc8eac39e47a3644"
        }
      ],
      "copyrightText": "NOASSERTION",
      "fileName": "usr/lib/.debug/libsubid.so.4.0.0",
      "fileTypes": [
        "BINARY"
      ],
      "licenseConcluded": "NOASSERTION",
      "licenseInfoInFiles": [
        "NOASSERTION"
      ]
    },
    {
      "SPDXID": "SPDXRef-PackagedFile-shadow-dbg-2",
      "checksums": [
        {
          "algorithm": "SHA1",
          "checksumValue": "898eabfdae442edab2a6b96a3a3d3dbcf7a42f4f"
        },
        {
          "algorithm": "SHA256",
          "checksumValue": "1394f55ab88b1bc3df9f5c908bcd8ae5850cd755f38400bc5facd5b4ddf48e28"
        }
      ],
      "copyrightText": "NOASSERTION",
      "fileName": "usr/sbin/.debug/grpconv",
      "fileTypes": [
        "BINARY"
      ],
      "licenseConcluded": "NOASSERTION",
      "licenseInfoInFiles": [
        "NOASSERTION"
      ]
    },
    {
      "SPDXID": "SPDXRef-PackagedFile-shadow-dbg-3",
      "checksums": [
        {
          "algorithm": "SHA1",
          "checksumValue": "0085258258a1f44c315c74660495d15cc47d18ea"
        },
        {
          "algorithm": "SHA256",
          "checksumValue": "53cca5af99d9ec2fe0aac5d0822843ffefad7b158ceb8d3ab924b0ac481887b7"
        }
      ],
      "copyrightText": "NOASSERTION",
      "fileName": "usr/sbin/.debug/groupmod",
      "fileTypes": [
        "BINARY"
      ],
      "licenseConcluded": "NOASSERTION",
      "licenseInfoInFiles": [
        "NOASSERTION"
      ]
    },
    {
      "SPDXID": "SPDXRef-PackagedFile-shadow-dbg-4",
      "checksums": [
        {
          "algorithm": "SHA1",
          "checksumValue": "0cf143878cf5bf2ee112d479c01f113297cc7713"
        },
        {
          "algorithm": "SHA256",
          "checksumValue": "a36f5dbc6045877ec0004eb42f00302d522665b727f47062836c71de97e533d4"
        }
      ],
      "copyrightText": "NOASSERTION",
      "fileName": "usr/sbin/.debug/groupadd",
      "fileTypes": [
        "BINARY"
      ],
      "licenseConcluded": "NOASSERTION",
      "licenseInfoInFiles": [
        "NOASSERTION"
      ]
    },
    {
      "SPDXID": "SPDXRef-PackagedFile-shadow-dbg-5",
      "checksums": [
        {
          "algorithm": "SHA1",
          "checksumValue": "eaffd7f8761af233da740157202605ccdf975173"
        },
        {
          "algorithm": "SHA256",
          "checksumValue": "23a75b6ca5ffbe24f44373cd3bb32951525b7b8b413362ee5ba4b24096c4bf62"
        }
      ],
      "copyrightText": "NOASSERTION",
      "fileName": "usr/sbin/.debug/chgpasswd",
      "fileTypes": [
        "BINARY"
      ],
      "licenseConcluded": "NOASSERTION",
      "licenseInfoInFiles": [
        "NOASSERTION"
      ]
    },
    {
      "SPDXID": "SPDXRef-PackagedFile-shadow-dbg-6",
      "checksums": [
        {
          "algorithm": "SHA1",
          "checksumValue": "c528db02579dfa6c445e1525c69fde18f05245f1"
        },
        {
          "algorithm": "SHA256",
          "checksumValue": "ad8080869de359acb8a25dab850ea8fb664021a4d982b4e23d2010b0dbc37326"
        }
      ],
      "copyrightText": "NOASSERTION",
      "fileName": "usr/sbin/.debug/logoutd",
      "fileTypes": [
        "BINARY"
      ],
      "licenseConcluded": "NOASSERTION",
      "licenseInfoInFiles": [
        "NOASSERTION"
      ]
    },
    {
      "SPDXID": "SPDXRef-PackagedFile-shadow-dbg-7",
      "checksums": [
        {
          "algorithm": "SHA1",
          "checksumValue": "7fd369ae8ff7bb4365315531e7f1df584a8eccc7"
        },
        {
          "algorithm": "SHA256",
          "checksumValue": "0555c49b7e15349308888371c3bf21c2c57374e4aa15251bf8ef749211e53600"
        }
      ],
      "copyrightText": "NOASSERTION",
      "fileName": "usr/sbin/.debug/pwunconv",
      "fileTypes": [
        "BINARY"
      ],
      "licenseConcluded": "NOASSERTION",
      "licenseInfoInFiles": [
        "NOASSERTION"
      ]
    },
    {
      "SPDXID": "SPDXRef-PackagedFile-shadow-dbg-8",
      "checksums": [
        {
          "algorithm": "SHA1",
          "checksumValue": "9baba093790a411b91c90d1af36ce2aed38d28ee"
        },
        {
          "algorithm": "SHA256",
          "checksumValue": "bcb67f62b11248d768de5a380c8a0eac4978623c0fef5712794f3be55804bc67"
        }
      ],
      "copyrightText": "NOASSERTION",
      "fileName": "usr/sbin/.debug/userdel",
      "fileTypes": [
        "BINARY"
      ],
      "licenseConcluded": "NOASSERTION",
      "licenseInfoInFiles": [
        "NOASSERTION"
      ]
    },
    {
      "SPDXID": "SPDXRef-PackagedFile-shadow-dbg-9",
      "checksums": [
        {
          "algorithm": "SHA1",
          "checksumValue": "03093af1a1c65c26f03161accef731dbe0b45f86"
        },
        {
          "algorithm": "SHA256",
          "checksumValue": "333919fb35cd7a942d4368d4ff8fe3ee801fe1e60edf55177450e2991a853107"
        }
      ],
      "copyrightText": "NOASSERTION",
      "fileName": "usr/sbin/.debug/useradd",
      "fileTypes": [
        "BINARY"
      ],
      "licenseConcluded": "NOASSERTION",
      "licenseInfoInFiles": [
        "NOASSERTION"
      ]
    },
    {
      "SPDXID": "SPDXRef-PackagedFile-shadow-dbg-10",
      "checksums": [
        {
          "algorithm": "SHA1",
          "checksumValue": "485d70a73541a31e8f7e48aab60dd12bcbfba4ef"
        },
        {
          "algorithm": "SHA256",
          "checksumValue": "5fda568be6a7fee7b5d3e80d509cde12cf212e953331a9f9532f53aa506dd988"
        }
      ],
      "copyrightText": "NOASSERTION",
      "fileName": "usr/sbin/.debug/pwconv",
      "fileTypes": [
        "BINARY"
      ],
      "licenseConcluded": "NOASSERTION",
      "licenseInfoInFiles": [
        "NOASSERTION"
      ]
    },
    {
      "SPDXID": "SPDXRef-PackagedFile-shadow-dbg-11",
      "checksums": [
        {
          "algorithm": "SHA1",
          "checksumValue": "50ff645228343117154fa05862f18ffcc69345c4"
        },
        {
          "algorithm": "SHA256",
          "checksumValue": "ccba622c8c995f9a8eb79176f3e806455ea2c95fa17dd4b01f87fe36a4c86dd5"
        }
      ],
      "copyrightText": "NOASSERTION",
      "fileName": "usr/sbin/.debug/grpunconv",
      "fileTypes": [
        "BINARY"
      ],
      "licenseConcluded": "NOASSERTION",
      "licenseInfoInFiles": [
        "NOASSERTION"
      ]
    },
    {
      "SPDXID": "SPDXRef-PackagedFile-shadow-dbg-12",
      "checksums": [
        {
          "algorithm": "SHA1",
          "checksumValue": "f7c08a82a82dd7b03fe84ff8e52c1aa45af4e03d"
        },
        {
          "algorithm": "SHA256",
          "checksumValue": "0875ebb89342b6ba7bf314a920531760be289f30d7f003f6633392e2e0f99898"
        }
      ],
      "copyrightText": "NOASSERTION",
      "fileName": "usr/sbin/.debug/pwck",
      "fileTypes": [
        "BINARY"
      ],
      "licenseConcluded": "NOASSERTION",
      "licenseInfoInFiles": [
        "NOASSERTION"
      ]
    },
    {
      "SPDXID": "SPDXRef-PackagedFile-shadow-dbg-13",
      "checksums": [
        {
          "algorithm": "SHA1",
          "checksumValue": "b513320e0fb7da7d9fb28253afa0cc864f5c3fe0"
        },
        {
          "algorithm": "SHA256",
          "checksumValue": "1cadaf85764b4d804c4cf60cd2fb3b10fbd14580e04c560543c9c81aac8cf10b"
        }
      ],
      "copyrightText": "NOASSERTION",
      "fileName": "usr/sbin/.debug/newusers",
      "fileTypes": [
        "BINARY"
      ],
      "licenseConcluded": "NOASSERTION",
      "licenseInfoInFiles": [
        "NOASSERTION"
      ]
    },
    {
      "SPDXID": "SPDXRef-PackagedFile-shadow-dbg-14",
      "checksums": [
        {
          "algorithm": "SHA1",
          "checksumValue": "b5c25531f20c960a9f93b9872a813ef9b22a2c37"
        },
        {
          "algorithm": "SHA256",
          "checksumValue": "cc6501493b0a12e773c746f7e90e5298f971c2cf76289977174ae64a6574ad5d"
        }
      ],
      "copyrightText": "NOASSERTION",
      "fileName": "usr/sbin/.debug/usermod",
      "fileTypes": [
        "BINARY"
      ],
      "licenseConcluded": "NOASSERTION",
      "licenseInfoInFiles": [
        "NOASSERTION"
      ]
    },
    {
      "SPDXID": "SPDXRef-PackagedFile-shadow-dbg-15",
      "checksums": [
        {
          "algorithm": "SHA1",
          "checksumValue": "ed1669de1f2097d76838edc95f463c802a3f1508"
        },
        {
          "algorithm": "SHA256",
          "checksumValue": "78cdb59b9bfc3bc7eeca0383585884db32ea5078c35ee920338b478d4c91256f"
        }
      ],
      "copyrightText": "NOASSERTION",
      "fileName": "usr/sbin/.debug/groupdel",
      "fileTypes": [
        "BINARY"
      ],
      "licenseConcluded": "NOASSERTION",
      "licenseInfoInFiles": [
        "NOASSERTION"
      ]
    },
    {
      "SPDXID": "SPDXRef-PackagedFile-shadow-dbg-16",
      "checksums": [
        {
          "algorithm": "SHA1",
          "checksumValue": "c47431ef0927ebbcfc7962ac6bc4d47fe81e28c1"
        },
        {
          "algorithm": "SHA256",
          "checksumValue": "1180bd0e41747603a84201257b5bd65a225fa5f678205576dfd475a52a6b0a56"
        }
      ],
      "copyrightText": "NOASSERTION",
      "fileName": "usr/sbin/.debug/groupmems",
      "fileTypes": [
        "BINARY"
      ],
      "licenseConcluded": "NOASSERTION",
      "licenseInfoInFiles": [
        "NOASSERTION"
      ]
    },
    {
      "SPDXID": "SPDXRef-PackagedFile-shadow-dbg-17",
      "checksums": [
        {
          "algorithm": "SHA1",
          "checksumValue": "6c97d6ff34ec7cc96a961f7b4b37883a8cdaffdf"
        },
        {
          "algorithm": "SHA256",
          "checksumValue": "7324f5b78834cd0daf4eb4a226bc99eac778c02c16db3597bfe82ab23e7d1eb7"
        }
      ],
      "copyrightText": "NOASSERTION",
      "fileName": "usr/sbin/.debug/grpck",
      "fileTypes": [
        "BINARY"
      ],
      "licenseConcluded": "NOASSERTION",
      "licenseInfoInFiles": [
        "NOASSERTION"
      ]
    },
    {
      "SPDXID": "SPDXRef-PackagedFile-shadow-dbg-18",
      "checksums": [
        {
          "algorithm": "SHA1",
          "checksumValue": "f3c6791274242d2ae8e8277752570743cffb89f3"
        },
        {
          "algorithm": "SHA256",
          "checksumValue": "f01344ca90b12e7647b2c8ff01cfb4c647a436d5b12f796454e112ccc12b7a44"
        }
      ],
      "copyrightText": "NOASSERTION",
      "fileName": "usr/sbin/.debug/chpasswd.shadow",
      "fileTypes": [
        "BINARY"
      ],
      "licenseConcluded": "NOASSERTION",
      "licenseInfoInFiles": [
        "NOASSERTION"
      ]
    },
    {
      "SPDXID": "SPDXRef-PackagedFile-shadow-dbg-19",
      "checksums": [
        {
          "algorithm": "SHA1",
          "checksumValue": "147e9e114ea9790101a788ebee155a779d6884f4"
        },
        {
          "algorithm": "SHA256",
          "checksumValue": "45061e85fe338a80a513bdc859a3fee3bc07d56b8ff36334b5067b250a323460"
        }
      ],
      "copyrightText": "NOASSERTION",
      "fileName": "usr/bin/.debug/expiry",
      "fileTypes": [
        "BINARY"
      ],
      "licenseConcluded": "NOASSERTION",
      "licenseInfoInFiles": [
        "NOASSERTION"
      ]
    },
    {
      "SPDXID": "SPDXRef-PackagedFile-shadow-dbg-20",
      "checksums": [
        {
          "algorithm": "SHA1",
          "checksumValue": "6d033332709ff7e1be6af77d9bb36f35cae2b2bf"
        },
        {
          "algorithm": "SHA256",
          "checksumValue": "7ad0997cb1a669cd7feeae3eefd9f2f61f242714057fae8c3527bac2e99ac3bf"
        }
      ],
      "copyrightText": "NOASSERTION",
      "fileName": "usr/bin/.debug/chage",
      "fileTypes": [
        "BINARY"
      ],
      "licenseConcluded": "NOASSERTION",
      "licenseInfoInFiles": [
        "NOASSERTION"
      ]
    },
    {
      "SPDXID": "SPDXRef-PackagedFile-shadow-dbg-21",
      "checksums": [
        {
          "algorithm": "SHA1",
          "checksumValue": "99634bacdafc41484a1dbf6696329192e87ed743"
        },
        {
          "algorithm": "SHA256",
          "checksumValue": "3ab2412eb3b8d2e01b6009023a47517b7e38292e015f57fa17721d4fad69fe1e"
        }
      ],
      "copyrightText": "NOASSERTION",
      "fileName": "usr/bin/.debug/chsh.shadow",
      "fileTypes": [
        "BINARY"
      ],
      "licenseConcluded": "NOASSERTION",
      "licenseInfoInFiles": [
        "NOASSERTION"
      ]
    },
    {
      "SPDXID": "SPDXRef-PackagedFile-shadow-dbg-22",
      "checksums": [
        {
          "algorithm": "SHA1",
          "checksumValue": "5fd0f4849799dc274bef8f2a494337e31975f221"
        },
        {
          "algorithm": "SHA256",
          "checksumValue": "0786cf21ba83062863253b555c286e66f3a9ddc3570d7ce7f0cb3dace28e4954"
        }
      ],
      "copyrightText": "NOASSERTION",
      "fileName": "usr/bin/.debug/newgidmap",
      "fileTypes": [
        "BINARY"
      ],
      "licenseConcluded": "NOASSERTION",
      "licenseInfoInFiles": [
        "NOASSERTION"
      ]
    },
    {
      "SPDXID": "SPDXRef-PackagedFile-shadow-dbg-23",
      "checksums": [
        {
          "algorithm": "SHA1",
          "checksumValue": "e434a1619f2c8c772456760e3f41914f51e0f807"
        },
        {
          "algorithm": "SHA256",
          "checksumValue": "2c7a70ad5d59992523a42cc7ab80d99839853b0085a14dd2bd7dfda81399344a"
        }
      ],
      "copyrightText": "NOASSERTION",
      "fileName": "usr/bin/.debug/newuidmap",
      "fileTypes": [
        "BINARY"
      ],
      "licenseConcluded": "NOASSERTION",
      "licenseInfoInFiles": [
        "NOASSERTION"
      ]
    },
    {
      "SPDXID": "SPDXRef-PackagedFile-shadow-dbg-24",
      "checksums": [
        {
          "algorithm": "SHA1",
          "checksumValue": "915ab85a933cf2f46e55750573a24309c4be5334"
        },
        {
          "algorithm": "SHA256",
          "checksumValue": "c287d88d2b95edeeee5aef27199410a2008a86f7c5ddb27be8f7d843c3de7603"
        }
      ],
      "copyrightText": "NOASSERTION",
      "fileName": "usr/bin/.debug/getsubids",
      "fileTypes": [
        "BINARY"
      ],
      "licenseConcluded": "NOASSERTION",
      "licenseInfoInFiles": [
        "NOASSERTION"
      ]
    },
    {
      "SPDXID": "SPDXRef-PackagedFile-shadow-dbg-25",
      "checksums": [
        {
          "algorithm": "SHA1",
          "checksumValue": "136ceb5353eb672b40a77c3df9ab51a145cba713"
        },
        {
          "algorithm": "SHA256",
          "checksumValue": "f99964757544b6cad8de8bde17f2ae7467de5ed0b00b84dbc6468afbcaed047a"
        }
      ],
      "copyrightText": "NOASSERTION",
      "fileName": "usr/bin/.debug/newgrp.shadow",
      "fileTypes": [
        "BINARY"
      ],
      "licenseConcluded": "NOASSERTION",
      "licenseInfoInFiles": [
        "NOASSERTION"
      ]
    },
    {
      "SPDXID": "SPDXRef-PackagedFile-shadow-dbg-26",
      "checksums": [
        {
          "algorithm": "SHA1",
          "checksumValue": "3681cc0828270b763d511217259391c92886d3b1"
        },
        {
          "algorithm": "SHA256",
          "checksumValue": "f240e60a01a4be1e1ecad9b709f196206dfc28b69332619f2c5c2b15d8b7d867"
        }
      ],
      "copyrightText": "NOASSERTION",
      "fileName": "usr/bin/.debug/gpasswd",
      "fileTypes": [
        "BINARY"
      ],
      "licenseConcluded": "NOASSERTION",
      "licenseInfoInFiles": [
        "NOASSERTION"
      ]
    },
    {
      "SPDXID": "SPDXRef-PackagedFile-shadow-dbg-27",
      "checksums": [
        {
          "algorithm": "SHA1",
          "checksumValue": "2fc8c435b36fe2868c80ab95ed0070d9cea772e1"
        },
        {
          "algorithm": "SHA256",
          "checksumValue": "d2040441b843e38f581339f4505f5e4db5a58c764f352cb19dbbeeec854aa33e"
        }
      ],
      "copyrightText": "NOASSERTION",
      "fileName": "usr/bin/.debug/groups.shadow",
      "fileTypes": [
        "BINARY"
      ],
      "licenseConcluded": "NOASSERTION",
      "licenseInfoInFiles": [
        "NOASSERTION"
      ]
    },
    {
      "SPDXID": "SPDXRef-PackagedFile-shadow-dbg-28",
      "checksums": [
        {
          "algorithm": "SHA1",
          "checksumValue": "54c48c0084235adee9b0756afd7f63e964c83314"
        },
        {
          "algorithm": "SHA256",
          "checksumValue": "0cb7b05122e091ae8bcf587c7769183c11d796a73bce247cdd4e90b6ecbaca34"
        }
      ],
      "copyrightText": "NOASSERTION",
      "fileName": "usr/bin/.debug/lastlog",
      "fileTypes": [
        "BINARY"
      ],
      "licenseConcluded": "NOASSERTION",
      "licenseInfoInFiles": [
        "NOASSERTION"
      ]
    },
    {
      "SPDXID": "SPDXRef-PackagedFile-shadow-dbg-29",
      "checksums": [
        {
          "algorithm": "SHA1",
          "checksumValue": "0f4f9161a650cff9fe70648d46685771b2e7e511"
        },
        {
          "algorithm": "SHA256",
          "checksumValue": "1c5c24d3d5c578b896f1220a3126546d05b661899a1c1dd98e9e01582a2f7df3"
        }
      ],
      "copyrightText": "NOASSERTION",
      "fileName": "usr/bin/.debug/chfn.shadow",
      "fileTypes": [
        "BINARY"
      ],
      "licenseConcluded": "NOASSERTION",
      "licenseInfoInFiles": [
        "NOASSERTION"
      ]
    },
    {
      "SPDXID": "SPDXRef-PackagedFile-shadow-dbg-30",
      "checksums": [
        {
          "algorithm": "SHA1",
          "checksumValue": "af01e36d1ad45f8acc8184f3229baf2f745b9a6b"
        },
        {
          "algorithm": "SHA256",
          "checksumValue": "24795b8679a3c802e7b62055144ca639aec88f74f133bd1cb8da756d63bdf6f5"
        }
      ],
      "copyrightText": "NOASSERTION",
      "fileName": "usr/bin/.debug/faillog",
      "fileTypes": [
        "BINARY"
      ],
      "licenseConcluded": "NOASSERTION",
      "licenseInfoInFiles": [
        "NOASSERTION"
      ]
    },
    {
      "SPDXID": "SPDXRef-PackagedFile-shadow-dbg-31",
      "checksums": [
        {
          "algorithm": "SHA1",
          "checksumValue": "5b1bcb392b4af9c56563c7ff474d160571f96557"
        },
        {
          "algorithm": "SHA256",
          "checksumValue": "2be6e4f9fda5b263a6d84cc96f0a8be8dbe03cf57f47bbe64e61ada587a74c16"
        }
      ],
      "copyrightText": "NOASSERTION",
      "fileName": "usr/bin/.debug/passwd.shadow",
      "fileTypes": [
        "BINARY"
      ],
      "licenseConcluded": "NOASSERTION",
      "licenseInfoInFiles": [
        "NOASSERTION"
      ]
    },
    {
      "SPDXID": "SPDXRef-PackagedFile-shadow-dbg-32",
      "checksums": [
        {
          "algorithm": "SHA1",
          "checksumValue": "b4b267a90371fb8bcb225786ce554159c17fb0e5"
        },
        {
          "algorithm": "SHA256",
          "checksumValue": "9f22de8d1b1ee4f674e0c5dbebb657f59f433d9d5784cade691c8c287fb94169"
        }
      ],
      "copyrightText": "NOASSERTION",
      "fileName": "sbin/.debug/nologin.shadow",
      "fileTypes": [
        "BINARY"
      ],
      "licenseConcluded": "NOASSERTION",
      "licenseInfoInFiles": [
        "NOASSERTION"
      ]
    },
    {
      "SPDXID": "SPDXRef-PackagedFile-shadow-dbg-33",
      "checksums": [
        {
          "algorithm": "SHA1",
          "checksumValue": "728e16cb87c3e0c9c8cbedac1b782b71702cde6c"
        },
        {
          "algorithm": "SHA256",
          "checksumValue": "697f099bbaf43423edad3ba78dafc2936e56c5dd5ab95a2d037b66a0463c38f6"
        }
      ],
      "copyrightText": "NOASSERTION",
      "fileName": "sbin/.debug/vipw.shadow",
      "fileTypes": [
        "BINARY"
      ],
      "licenseConcluded": "NOASSERTION",
      "licenseInfoInFiles": [
        "NOASSERTION"
      ]
    },
    {
      "SPDXID": "SPDXRef-PackagedFile-shadow-dbg-34",
      "checksums": [
        {
          "algorithm": "SHA1",
          "checksumValue": "e27551295d48078d9ba6804e454b34ad731731a3"
        },
        {
          "algorithm": "SHA256",
          "checksumValue": "25a53365b12a91fe67215ea166173f90de52c80c03a8e5ebd0e503b26e391437"
        }
      ],
      "copyrightText": "NOASSERTION",
      "fileName": "bin/.debug/login.shadow",
      "fileTypes": [
        "BINARY"
      ],
      "licenseConcluded": "NOASSERTION",
      "licenseInfoInFiles": [
        "NOASSERTION"
      ]
    },
    {
      "SPDXID": "SPDXRef-PackagedFile-shadow-dbg-35",
      "checksums": [
        {
          "algorithm": "SHA1",
          "checksumValue": "c60e65010f064858b3f964e0a5ef97b9e99de0ab"
        },
        {
          "algorithm": "SHA256",
          "checksumValue": "374db65f5239ff48dcba638602fb4cf8b452c1b4ea6d2076ca0c96c57807893d"
        }
      ],
      "copyrightText": "NOASSERTION",
      "fileName": "bin/.debug/su.shadow",
      "fileTypes": [
        "BINARY"
      ],
      "licenseConcluded": "NOASSERTION",
      "licenseInfoInFiles": [
        "NOASSERTION"
      ]
    }
  ],
  "name": "shadow-dbg",
  "packages": [
    {
      "SPDXID": "SPDXRef-Package-shadow-dbg",
      "copyrightText": "NOASSERTION",
      "downloadLocation": "NOASSERTION",
      "hasFiles": [
        "SPDXRef-PackagedFile-shadow-dbg-1",
        "SPDXRef-PackagedFile-shadow-dbg-2",
        "SPDXRef-PackagedFile-shadow-dbg-3",
        "SPDXRef-PackagedFile-shadow-dbg-4",
        "SPDXRef-PackagedFile-shadow-dbg-5",
        "SPDXRef-PackagedFile-shadow-dbg-6",
        "SPDXRef-PackagedFile-shadow-dbg-7",
        "SPDXRef-PackagedFile-shadow-dbg-8",
        "SPDXRef-PackagedFile-shadow-dbg-9",
        "SPDXRef-PackagedFile-shadow-dbg-10",
        "SPDXRef-PackagedFile-shadow-dbg-11",
        "SPDXRef-PackagedFile-shadow-dbg-12",
        "SPDXRef-PackagedFile-shadow-dbg-13",
        "SPDXRef-PackagedFile-shadow-dbg-14",
        "SPDXRef-PackagedFile-shadow-dbg-15",
        "SPDXRef-PackagedFile-shadow-dbg-16",
        "SPDXRef-PackagedFile-shadow-dbg-17",
        "SPDXRef-PackagedFile-shadow-dbg-18",
        "SPDXRef-PackagedFile-shadow-dbg-19",
        "SPDXRef-PackagedFile-shadow-dbg-20",
        "SPDXRef-PackagedFile-shadow-dbg-21",
        "SPDXRef-PackagedFile-shadow-dbg-22",
        "SPDXRef-PackagedFile-shadow-dbg-23",
        "SPDXRef-PackagedFile-shadow-dbg-24",
        "SPDXRef-PackagedFile-shadow-dbg-25",
        "SPDXRef-PackagedFile-shadow-dbg-26",
        "SPDXRef-PackagedFile-shadow-dbg-27",
        "SPDXRef-PackagedFile-shadow-dbg-28",
        "SPDXRef-PackagedFile-shadow-dbg-29",
        "SPDXRef-PackagedFile-shadow-dbg-30",
        "SPDXRef-PackagedFile-shadow-dbg-31",
        "SPDXRef-PackagedFile-shadow-dbg-32",
        "SPDXRef-PackagedFile-shadow-dbg-33",
        "SPDXRef-PackagedFile-shadow-dbg-34",
        "SPDXRef-PackagedFile-shadow-dbg-35"
      ],
      "licenseConcluded": "NOASSERTION",
      "licenseDeclared": "BSD-3-Clause",
      "licenseInfoFromFiles": [
        "NOASSERTION"
      ],
      "name": "shadow-dbg",
      "packageSupplier": "Organization: OpenEmbedded ()",
      "packageVerificationCode": {
        "packageVerificationCodeValue": "9e726e2015187a137e134563e42cf44e2838c5f2"
      },
      "versionInfo": "4.11.1"
    }
  ],
  "relationships": [
    {
      "relatedSpdxElement": "DocumentRef-recipe-shadow:SPDXRef-Recipe-shadow",
      "relationshipType": "GENERATED_FROM",
      "spdxElementId": "SPDXRef-Package-shadow-dbg"
    },
    {
      "relatedSpdxElement": "SPDXRef-Package-shadow-dbg",
      "relationshipType": "DESCRIBES",
      "spdxElementId": "SPDXRef-DOCUMENT"
    },
    {
      "relatedSpdxElement": "SPDXRef-PackagedFile-shadow-dbg-1",
      "relationshipType": "CONTAINS",
      "spdxElementId": "SPDXRef-Package-shadow-dbg"
    },
    {
      "relatedSpdxElement": "SPDXRef-PackagedFile-shadow-dbg-2",
      "relationshipType": "CONTAINS",
      "spdxElementId": "SPDXRef-Package-shadow-dbg"
    },
    {
      "relatedSpdxElement": "SPDXRef-PackagedFile-shadow-dbg-3",
      "relationshipType": "CONTAINS",
      "spdxElementId": "SPDXRef-Package-shadow-dbg"
    },
    {
      "relatedSpdxElement": "SPDXRef-PackagedFile-shadow-dbg-4",
      "relationshipType": "CONTAINS",
      "spdxElementId": "SPDXRef-Package-shadow-dbg"
    },
    {
      "relatedSpdxElement": "SPDXRef-PackagedFile-shadow-dbg-5",
      "relationshipType": "CONTAINS",
      "spdxElementId": "SPDXRef-Package-shadow-dbg"
    },
    {
      "relatedSpdxElement": "SPDXRef-PackagedFile-shadow-dbg-6",
      "relationshipType": "CONTAINS",
      "spdxElementId": "SPDXRef-Package-shadow-dbg"
    },
    {
      "relatedSpdxElement": "SPDXRef-PackagedFile-shadow-dbg-7",
      "relationshipType": "CONTAINS",
      "spdxElementId": "SPDXRef-Package-shadow-dbg"
    },
    {
      "relatedSpdxElement": "SPDXRef-PackagedFile-shadow-dbg-8",
      "relationshipType": "CONTAINS",
      "spdxElementId": "SPDXRef-Package-shadow-dbg"
    },
    {
      "relatedSpdxElement": "SPDXRef-PackagedFile-shadow-dbg-9",
      "relationshipType": "CONTAINS",
      "spdxElementId": "SPDXRef-Package-shadow-dbg"
    },
    {
      "relatedSpdxElement": "SPDXRef-PackagedFile-shadow-dbg-10",
      "relationshipType": "CONTAINS",
      "spdxElementId": "SPDXRef-Package-shadow-dbg"
    },
    {
      "relatedSpdxElement": "SPDXRef-PackagedFile-shadow-dbg-11",
      "relationshipType": "CONTAINS",
      "spdxElementId": "SPDXRef-Package-shadow-dbg"
    },
    {
      "relatedSpdxElement": "SPDXRef-PackagedFile-shadow-dbg-12",
      "relationshipType": "CONTAINS",
      "spdxElementId": "SPDXRef-Package-shadow-dbg"
    },
    {
      "relatedSpdxElement": "SPDXRef-PackagedFile-shadow-dbg-13",
      "relationshipType": "CONTAINS",
      "spdxElementId": "SPDXRef-Package-shadow-dbg"
    },
    {
      "relatedSpdxElement": "SPDXRef-PackagedFile-shadow-dbg-14",
      "relationshipType": "CONTAINS",
      "spdxElementId": "SPDXRef-Package-shadow-dbg"
    },
    {
      "relatedSpdxElement": "SPDXRef-PackagedFile-shadow-dbg-15",
      "relationshipType": "CONTAINS",
      "spdxElementId": "SPDXRef-Package-shadow-dbg"
    },
    {
      "relatedSpdxElement": "SPDXRef-PackagedFile-shadow-dbg-16",
      "relationshipType": "CONTAINS",
      "spdxElementId": "SPDXRef-Package-shadow-dbg"
    },
    {
      "relatedSpdxElement": "SPDXRef-PackagedFile-shadow-dbg-17",
      "relationshipType": "CONTAINS",
      "spdxElementId": "SPDXRef-Package-shadow-dbg"
    },
    {
      "relatedSpdxElement": "SPDXRef-PackagedFile-shadow-dbg-18",
      "relationshipType": "CONTAINS",
      "spdxElementId": "SPDXRef-Package-shadow-dbg"
    },
    {
      "relatedSpdxElement": "SPDXRef-PackagedFile-shadow-dbg-19",
      "relationshipType": "CONTAINS",
      "spdxElementId": "SPDXRef-Package-shadow-dbg"
    },
    {
      "relatedSpdxElement": "SPDXRef-PackagedFile-shadow-dbg-20",
      "relationshipType": "CONTAINS",
      "spdxElementId": "SPDXRef-Package-shadow-dbg"
    },
    {
      "relatedSpdxElement": "SPDXRef-PackagedFile-shadow-dbg-21",
      "relationshipType": "CONTAINS",
      "spdxElementId": "SPDXRef-Package-shadow-dbg"
    },
    {
      "relatedSpdxElement": "SPDXRef-PackagedFile-shadow-dbg-22",
      "relationshipType": "CONTAINS",
      "spdxElementId": "SPDXRef-Package-shadow-dbg"
    },
    {
      "relatedSpdxElement": "SPDXRef-PackagedFile-shadow-dbg-23",
      "relationshipType": "CONTAINS",
      "spdxElementId": "SPDXRef-Package-shadow-dbg"
    },
    {
      "relatedSpdxElement": "SPDXRef-PackagedFile-shadow-dbg-24",
      "relationshipType": "CONTAINS",
      "spdxElementId": "SPDXRef-Package-shadow-dbg"
    },
    {
      "relatedSpdxElement": "SPDXRef-PackagedFile-shadow-dbg-25",
      "relationshipType": "CONTAINS",
      "spdxElementId": "SPDXRef-Package-shadow-dbg"
    },
    {
      "relatedSpdxElement": "SPDXRef-PackagedFile-shadow-dbg-26",
      "relationshipType": "CONTAINS",
      "spdxElementId": "SPDXRef-Package-shadow-dbg"
    },
    {
      "relatedSpdxElement": "SPDXRef-PackagedFile-shadow-dbg-27",
      "relationshipType": "CONTAINS",
      "spdxElementId": "SPDXRef-Package-shadow-dbg"
    },
    {
      "relatedSpdxElement": "SPDXRef-PackagedFile-shadow-dbg-28",
      "relationshipType": "CONTAINS",
      "spdxElementId": "SPDXRef-Package-shadow-dbg"
    },
    {
      "relatedSpdxElement": "SPDXRef-PackagedFile-shadow-dbg-29",
      "relationshipType": "CONTAINS",
      "spdxElementId": "SPDXRef-Package-shadow-dbg"
    },
    {
      "relatedSpdxElement": "SPDXRef-PackagedFile-shadow-dbg-30",
      "relationshipType": "CONTAINS",
      "spdxElementId": "SPDXRef-Package-shadow-dbg"
    },
    {
      "relatedSpdxElement": "SPDXRef-PackagedFile-shadow-dbg-31",
      "relationshipType": "CONTAINS",
      "spdxElementId": "SPDXRef-Package-shadow-dbg"
    },
    {
      "relatedSpdxElement": "SPDXRef-PackagedFile-shadow-dbg-32",
      "relationshipType": "CONTAINS",
      "spdxElementId": "SPDXRef-Package-shadow-dbg"
    },
    {
      "relatedSpdxElement": "SPDXRef-PackagedFile-shadow-dbg-33",
      "relationshipType": "CONTAINS",
      "spdxElementId": "SPDXRef-Package-shadow-dbg"
    },
    {
      "relatedSpdxElement": "SPDXRef-PackagedFile-shadow-dbg-34",
      "relationshipType": "CONTAINS",
      "spdxElementId": "SPDXRef-Package-shadow-dbg"
    },
    {
      "relatedSpdxElement": "SPDXRef-PackagedFile-shadow-dbg-35",
      "relationshipType": "CONTAINS",
      "spdxElementId": "SPDXRef-Package-shadow-dbg"
    }
  ],
  "spdxVersion": "SPDX-2.2"
}
